planb/__init__.py
planb/__main__.py
planb/admin.py
planb/apps.py
planb/backends.py
planb/checks.py
planb/default_settings.py
planb/factories.py
planb/forms.py
planb/models.py
planb/monkeypatch.py
planb/signals.py
planb/tasks.py
planb/transport.py
planb/urls.py
planb/utils.py
planb/views.py
planb/common/__init__.py
planb/common/customyaml.py
planb/common/fields.py
planb/common/human.py
planb/common/log2.py
planb/common/subprocess2.py
planb/common/test_subprocess2.py
planb/common/templatetags/__init__.py
planb/common/templatetags/rst.py
planb/contrib/__init__.py
planb/contrib/billing.py
planb/fixtures/planb_jobs.xml
planb/management/__init__.py
planb/management/base.py
planb/management/commands/__init__.py
planb/management/commands/bclone.py
planb/management/commands/blist.py
planb/management/commands/bqcluster.py
planb/management/commands/bqueueall.py
planb/management/commands/bqueueflush.py
planb/management/commands/breport.py
planb/management/commands/bstats.py
planb/management/commands/confexport.py
planb/management/commands/slist.py
planb/migrations/0001_initial.py
planb/migrations/0002_hostconfig_add_description.py
planb/migrations/0003_auto_20170710_1814.py
planb/migrations/0004_refactor_transportfield.py
planb/migrations/0005_add_backuprun.py
planb/migrations/0006_last_monthly_report.py
planb/migrations/0007_first_and_last_fail.py
planb/migrations/0008_average_duration.py
planb/migrations/0009_rename_total_size_mb.py
planb/migrations/0010_drop_keep_booleans.py
planb/migrations/0011_hostconfig_to_fileset.py
planb/migrations/0012_drop_rsync_config.py
planb/migrations/0013_optional_dutree_and_is_booleans.py
planb/migrations/0014_add_backuprun_attributes.py
planb/migrations/0015_fileset_storage.py
planb/migrations/0016_auto_20200505_1619.py
planb/migrations/0017_migrate_retention.py
planb/migrations/0018_auto_20200505_1638.py
planb/migrations/0019_add_fileset_tags.py
planb/migrations/0020_backuprun_snapshot_name.py
planb/migrations/__init__.py
planb-1.7.dist-info/LICENSE
planb-1.7.dist-info/METADATA
planb-1.7.dist-info/WHEEL
planb-1.7.dist-info/entry_points.txt
planb-1.7.dist-info/top_level.txt
planb-1.7.dist-info/RECORD
