Metadata-Version: 2.1
Name: planb
Version: 1.7
Summary: PlanB automates remote SSH+rsync backups
Home-page: https://github.com/ossobv/planb
Author: Alex Boonstra, Harm Geerts, Walter Doekes, OSSO B.V.
Author-email: wjdoekes+planb@osso.nl
License: GPLv3+
Platform: linux
Classifier: Development Status :: 4 - Beta
Classifier: Environment :: Web Environment
Classifier: Framework :: Django
Classifier: Framework :: Django :: 2
Classifier: Framework :: Django :: 3
Classifier: Intended Audience :: System Administrators
Classifier: License :: OSI Approved :: GNU General Public License v3 or later (GPLv3+)
Classifier: Operating System :: POSIX :: Linux
Classifier: Programming Language :: Python
Classifier: Programming Language :: Python :: 3
Classifier: Topic :: System :: Archiving :: Backup
License-File: LICENSE
Requires-Dist: Django (<3.3,>=2.2)
Requires-Dist: django-q (<2,>=1.2.1)
Requires-Dist: django-multi-email-field (<0.7,>=0.6.1)
Requires-Dist: dutree (<2,>=1.6)
Requires-Dist: PyYAML (>=5.1.1)
Requires-Dist: redis
Requires-Dist: setproctitle (<2,>=1.1.8)
Requires-Dist: python-dateutil (<3,>=2.8.1)
